## Задача 1
> _Изучите возможности просмотра байткода ВМ CPython._
> _Опишите по шагам, что делает каждая из следующих команд (приведите эквивалентное выражение на Python)_

<table>
  <tr><td>11 0 LOAD_FAST 0 (x)</td><td>Значение локальной переменной в стек</td></tr>
  <tr><td>2 LOAD_CONST 1 (10)</td><td>Значение константы 1 в стек</td></tr>
  <tr><td>4 BINARY_MULTIPLY</td><td>Умножение двух значений с вершины стека. Резултат - на вершину.</td></tr>
  <tr><td>6 LOAD_CONST 2 (42)</td><td>Значение константы 42 в стек</td></tr>
  <tr><td>8 BINARY_ADD</td><td>Сложение двух значений с вершины стека. Резултат - на вершину.</td></tr>
  <tr><td>10 RETURN_VALUE</td><td>Вернуть значение с вершины стека</td></tr>
</table>

Эквивалент на питоне:
```py
return (x * 10) + 42
```



## Задача 2
> Что делает следующий байткод (опишите шаги его работы)? Это известная функция, назовите ее.

```
  5           0 LOAD_CONST               1 (1)
              2 STORE_FAST               1 (r)

  6     >>    4 LOAD_FAST                0 (n)
              6 LOAD_CONST               1 (1)
              8 COMPARE_OP               4 (>)
             10 POP_JUMP_IF_FALSE       30

  7          12 LOAD_FAST                1 (r)
             14 LOAD_FAST                0 (n)
             16 INPLACE_MULTIPLY
             18 STORE_FAST               1 (r)

  8          20 LOAD_FAST                0 (n)
             22 LOAD_CONST               1 (1)
             24 INPLACE_SUBTRACT
             26 STORE_FAST               0 (n)
             28 JUMP_ABSOLUTE            4

  9     >>   30 LOAD_FAST                1 (r)
             32 RETURN_VALUE
```

<table>
  <tr><td>5</td><td>Константа 1 в стек. Сохранение константы в переменную r</td></tr>
  <tr><td>6</td><td>Значение переменной n в стек. Константа 1 в стек. Сравнение (n>1). Прерывание если false.</td></tr>
  <tr><td>7</td><td>Значение переменной r в стек. Значение переменной n в стек. Умножение r * n; сохранение результата в r. Сохраняет обновлённое значение в r.</td></tr>
  <tr><td>8</td><td>Значение переменной n. Константа 1. Вычитание 1 из значения n; обновление n.Сохранение обновлённого значение в n. Возвращение к началу цикла (инструкция 4); проверка условия.</td></tr>
  <tr><td>9</td><td>Значение переменной r. Возврат значения r как результат функции</td></tr>
</table>

Эквивалент на питоне: факториал
```py
def factorial(n):
    r = 1
    while n > 1:
        r *= n
        n -= 1
    return r
```

## Задача 3
> Приведите результаты из задач 1 и 2 для виртуальной машины JVM (Java).

Задание 1
```java
while (x != 0) {
 x -= 1;
}
return x + 1;
```

```java
0: iload_0       
1: ifeq 11        
4: iinc 0, -1      
7: goto 0         
11: iload_0         
12: iconst_1        
13: iadd           
14: ireturn         
```

Задание 2
```java
public static int factorial(int n) {
    int r = 1;
    while (n > 1) {
        r *= n;
        n -= 1;
    }
    return r;
}
```

```java
0: iconst_1     
1: istore_1      
2: iload_0        
3: iconst_1        
4: if_icmple 19   
7: iload_1        
8: iload_0       
9: imul         
10: istore_1      
11: iload_0       
12: iconst_1      
13: isub          
14: istore_0      
15: goto 2         
19: iload_1        
20: ireturn        
```

## Задача 4
> Работа с qemu. Скачать и установить ISO-образ Alpine Linux для виртуальных машин с официального сайта. Создать с помощью qemu образ жесткого диска (опция -f qcow2). Объем диска 500 Мб. Запустить Alpine Linux с CD-ROM. Установить систему на sda. Изменить motd. Загрузиться уже с sda. Прислать полный список команд для установки и загрузки, а также скриншот с motd, где фигурируют ваши имя и фамилия.
